amocatlas/__init__.py
amocatlas/_version.py
amocatlas/amoc_registry.txt
amocatlas/logger.py
amocatlas/plotters.py
amocatlas/read_41n.py
amocatlas/read_dso.py
amocatlas/read_fw2015.py
amocatlas/read_mocha.py
amocatlas/read_move.py
amocatlas/read_osnap.py
amocatlas/read_rapid.py
amocatlas/read_samba.py
amocatlas/readers.py
amocatlas/standardise.py
amocatlas/tools.py
amocatlas/utilities.py
amocatlas/writers.py
amocatlas/metadata/41n_array.yml
amocatlas/metadata/dso_array.yml
amocatlas/metadata/fw2015_array.yml
amocatlas/metadata/mocha_array.yml
amocatlas/metadata/move_array.yml
amocatlas/metadata/osnap_array.yml
amocatlas/metadata/rapid_array.yml
amocatlas/metadata/samba_array.yml
amocatlas-0.1.1.dist-info/licenses/LICENSE
amocatlas-0.1.1.dist-info/METADATA
amocatlas-0.1.1.dist-info/WHEEL
amocatlas-0.1.1.dist-info/top_level.txt
amocatlas-0.1.1.dist-info/RECORD
