Metadata-Version: 2.4
Name: AMOCatlas
Version: 0.1.1
Summary: Python project to read data from arrays measuring the Atlantic meridional overturning circulation
Maintainer-email: Eleanor Frajka-Williams <eleanorfrajka@gmail.com>
License: MIT License
Project-URL: documentation, https://github.com/AMOCcommunity/AMOCatlas
Project-URL: homepage, https://github.com/AMOCcommunity/AMOCatlas
Project-URL: repository, https://github.com/AMOCcommunity/AMOCatlas
Classifier: Programming Language :: Python :: 3 :: Only
Classifier: Programming Language :: Python :: 3.9
Classifier: Programming Language :: Python :: 3.10
Classifier: Programming Language :: Python :: 3.11
Classifier: Programming Language :: Python :: 3.12
Requires-Python: >=3.9
License-File: LICENSE
Requires-Dist: numpy>=1.23
Requires-Dist: pandas>=2.0
Requires-Dist: xarray>=2023.12.0
Requires-Dist: netcdf4>=1.6
Requires-Dist: scipy>=1.10
Requires-Dist: matplotlib>=3.7
Dynamic: license-file
